flink_ml_framework/startup.py
flink_ml_framework/context.py
flink_ml_framework/java_file_c.cpython-37m-x86_64-linux-gnu.so
flink_ml_framework/node_service_pb2_grpc.py
flink_ml_framework/node_pb2.py
flink_ml_framework/__init__.py
flink_ml_framework/java_file.py
flink_ml_framework/version.py
flink_ml_framework/node_service_pb2.py
flink_ml_framework-0.4.dev20220209.dist-info/METADATA
flink_ml_framework-0.4.dev20220209.dist-info/top_level.txt
flink_ml_framework-0.4.dev20220209.dist-info/RECORD
flink_ml_framework-0.4.dev20220209.dist-info/WHEEL
