Metadata-Version: 2.1
Name: flink-ml-framework
Version: 0.4.dev20220209
Summary: UNKNOWN
Home-page: https://github.com/flink-extended/dl-on-flink
License: https://www.apache.org/licenses/LICENSE-2.0
Platform: UNKNOWN
Requires-Python: >=3.6,<3.9
Requires-Dist: grpcio (>=1.24.3)
Requires-Dist: protobuf (<3.18)
